lino_cosi/__init__.py
lino_cosi/migrate.py
lino_cosi/config/trading/Invoice/trailer.body.html
lino_cosi/lib/__init__.py
lino_cosi/lib/contacts/__init__.py
lino_cosi/lib/contacts/models.py
lino_cosi/lib/contacts/fixtures/__init__.py
lino_cosi/lib/contacts/fixtures/checkdata.py
lino_cosi/lib/contacts/fixtures/demo.py
lino_cosi/lib/contacts/fixtures/demo2.py
lino_cosi/lib/contacts/fixtures/std.py
lino_cosi/lib/contacts/management/__init__.py
lino_cosi/lib/contacts/management/commands/__init__.py
lino_cosi/lib/cosi/__init__.py
lino_cosi/lib/cosi/help_texts.py
lino_cosi/lib/cosi/layouts.py
lino_cosi/lib/cosi/models.py
lino_cosi/lib/cosi/settings.py
lino_cosi/lib/cosi/user_types.py
lino_cosi/lib/cosi/locale/django.pot
lino_cosi/lib/cosi/locale/de/LC_MESSAGES/django.mo
lino_cosi/lib/cosi/locale/de/LC_MESSAGES/django.po
lino_cosi/lib/cosi/locale/es/LC_MESSAGES/django.mo
lino_cosi/lib/cosi/locale/es/LC_MESSAGES/django.po
lino_cosi/lib/cosi/locale/et/LC_MESSAGES/django.mo
lino_cosi/lib/cosi/locale/et/LC_MESSAGES/django.po
lino_cosi/lib/cosi/locale/fr/LC_MESSAGES/django.mo
lino_cosi/lib/cosi/locale/fr/LC_MESSAGES/django.po
lino_cosi/lib/cosi/locale/nl/LC_MESSAGES/django.mo
lino_cosi/lib/cosi/locale/nl/LC_MESSAGES/django.po
lino_cosi/lib/cosi/locale/pt/LC_MESSAGES/django.mo
lino_cosi/lib/cosi/locale/pt/LC_MESSAGES/django.po
lino_cosi/lib/cosi/locale/pt-br/LC_MESSAGES/django.mo
lino_cosi/lib/cosi/locale/pt-br/LC_MESSAGES/django.po
lino_cosi/lib/cosi/locale/zh_Hant/LC_MESSAGES/django.po
lino_cosi/lib/products/__init__.py
lino_cosi/lib/products/models.py
lino_cosi/lib/products/fixtures/__init__.py
lino_cosi/lib/products/fixtures/food.py
lino_cosi/lib/products/fixtures/furniture.py
lino_cosi/lib/trading/__init__.py
lino_cosi/lib/trading/models.py
lino_cosi/lib/trading/fixtures/__init__.py
lino_cosi/lib/trading/fixtures/demo_bookings.py
lino_cosi/lib/trading/fixtures/std.py
lino_cosi/lib/users/__init__.py
lino_cosi/lib/users/models.py
lino_cosi/lib/users/ui.py
lino_cosi-25.3.0.dist-info/METADATA
lino_cosi-25.3.0.dist-info/WHEEL
lino_cosi-25.3.0.dist-info/licenses/AUTHORS.rst
lino_cosi-25.3.0.dist-info/licenses/COPYING
lino_cosi-25.3.0.dist-info/RECORD
